<?xml version="1.0" encoding="UTF-8"?>
<ConnList sysname="Cellular Mobile Telephone"><item type="conn" code="C15"><note></note><partNo>7140-3303</partNo></item><item type="conn" code="C17"><note></note><partNo>90980-10998</partNo></item><item type="conn" code="C18"><note></note><partNo>90980-10798</partNo></item><item type="conn" code="J 7"><note></note><partNo>90980-11542</partNo></item><item type="conn" code="J16"><note></note><partNo>90980-11542</partNo></item><item type="conn" code="J22"><note></note><partNo>90980-10976</partNo></item><item type="conn" code="J45"><note></note><partNo>90980-10976</partNo></item><item type="conn" code="R15"><note></note><partNo>90980-10935</partNo></item><item type="conn" code="R16"><note></note><partNo>90980-10935</partNo></item><item type="conn" code="S10"><note></note><partNo>90980-10997</partNo></item><item type="conn" code="S11"><note></note><partNo>90980-10996</partNo></item><item type="conn" code="T 4"><note></note><partNo>90980-11369</partNo></item><item type="conn" code="T 8"><note></note><partNo>90980-10802</partNo></item><item type="conn" code="T 9"><note></note><partNo>90980-10803</partNo></item></ConnList>
