<?xml version="1.0" encoding="UTF-8"?>
<ItemList ver="1.0" sysname="Radiator Fan and Condenser Fan"><item type="conn" code="A2" no="1"><ref type="g_routing" page="68"/><name></name><note>LHD</note></item><item type="conn" code="A2" no="2"><ref type="g_routing" page="82"/><name></name><note>RHD</note></item><item type="conn" code="A4" no="3"><ref type="g_routing" page="68"/><name></name><note>LHD</note></item><item type="conn" code="A4" no="4"><ref type="g_routing" page="82"/><name></name><note>RHD</note></item><item type="conn" code="J5" no="5"><ref type="g_routing" page="70"/><name></name><note>LHD</note></item><item type="conn" code="J15" no="6"><ref type="g_routing" page="74"/><name></name><note>LHD</note></item><item type="conn" code="J29" no="7"><ref type="g_routing" page="84"/><name></name><note>RHD</note></item><item type="conn" code="J36" no="8"><ref type="g_routing" page="88"/><name></name><note>RHD</note></item><item type="conn" code="R1" no="9"><ref type="g_routing" page="70"/><name></name><note>LHD</note></item><item type="conn" code="R1" no="10"><ref type="g_routing" page="84"/><name></name><note>RHD</note></item><item type="conn" code="W4" no="11"><ref type="g_routing" page="70"/><name></name><note>LHD</note></item><item type="conn" code="W4" no="12"><ref type="g_routing" page="84"/><name></name><note>RHD</note></item><item type="rb" code="1" no="1"><ref type="f_relay" page="54"/><name></name><note>LHD</note></item><item type="rb" code="1" no="2"><ref type="f_relay" page="54"/><name></name><note>RHD</note></item><item type="rb" code="3" no="3"><ref type="f_relay" page="56"/><name></name><note></note></item><item type="jb" code="1G" no="1"><ref type="f_relay" page="59"/><name></name><note>LHD</note></item><item type="jb" code="1G" no="2"><ref type="f_relay" page="59"/><name></name><note>RHD</note></item><item type="w2w" code="EB1" no="1"><ref type="g_routing" page="96"/><name></name><note>LHD</note></item><item type="w2w" code="EB1" no="2"><ref type="g_routing" page="106"/><name></name><note>RHD</note></item><item type="w2w" code="EB2" no="3"><ref type="g_routing" page="96"/><name></name><note>LHD</note></item><item type="w2w" code="EB2" no="4"><ref type="g_routing" page="106"/><name></name><note>RHD</note></item><item type="w2w" code="IA1" no="5"><ref type="g_routing" page="98"/><name></name><note>LHD</note></item><item type="w2w" code="IA1" no="6"><ref type="g_routing" page="108"/><name></name><note>RHD</note></item><item type="w2w" code="IA2" no="7"><ref type="g_routing" page="108"/><name></name><note>RHD</note></item><item type="w2w" code="IC1" no="8"><ref type="g_routing" page="98"/><name></name><note>LHD</note></item><item type="w2w" code="IC1" no="9"><ref type="g_routing" page="108"/><name></name><note>RHD</note></item><item type="w2w" code="II2" no="10"><ref type="g_routing" page="100"/><name></name><note>LHD</note></item><item type="gp" code="EB" no="1"><ref type="g_routing" page="96"/><name></name><note>LHD</note></item><item type="gp" code="EB" no="2"><ref type="g_routing" page="106"/><name></name><note>RHD</note></item><item type="gp" code="EE" no="3"><ref type="g_routing" page="96"/><name></name><note>LHD</note></item><item type="gp" code="EE" no="4"><ref type="g_routing" page="106"/><name></name><note>RHD</note></item><item type="sp" code="E4" no="1"><ref type="g_routing" page="96"/><name></name><note>LHD</note></item><item type="sp" code="E4" no="2"><ref type="g_routing" page="106"/><name></name><note>RHD</note></item></ItemList>
